{
	"type": "forge:ore_shaped",
	"result": {
		"item": {
			"item": "basemetals:diamond_arrow"
		},
		"count": 4
	},
	"pattern": [
		"x",
		"y",
		"z"
	],
	"key": {
		"x": {
			"type": "forge:ore_dict",
			"ore": "nuggetDiamond"
		},
		"y": {
			"item": "basemetals:diamond_rod"
		},
		"z": {
			"item": "basemetals:diamond_feather"
		}
	},
	"conditions": [
		{
			"type": "forge:and",
			"values": [
				{
					"type": "basemetals:enabled",
					"optionName": "material",
					"optionValue": "Diamond"
				},
				{
					"type": "basemetals:enabled",
					"optionName": "thing",
					"optionValue": "BowAndArrow"
				},
				{
					"type": "basemetals:enabled",
					"optionName": "thing",
					"optionValue": "Basics"
				}
			]
		}
	],
	"group": "vanilla"
}