{
	"type": "forge:ore_shaped",
	"result": {
		"item": "basemetals:emerald_crackhammer"
	},
	"pattern": [
		"x",
		"y",
		"y"
	],
	"key": {
		"x": "ore:blockEmerald",
		"y": "ore:stickWood"
	},
	"conditions": [
		{
			"type": "forge:and",
			"values": [
				{
					"type": "basemetals:enabled",
					"optionName": "material",
					"optionValue": "Emerald"
				},
				{
					"type": "basemetals:enabled",
					"optionName": "thing",
					"optionValue": "Basics"
				},
				{
					"type": "basemetals:hammer"
				}
			]
		}
	],
	"group": "vanilla"
}